Metadata-Version: 1.1
Name: bf2c
Version: 0.0.1
Summary: Brainf*ck to C programming language converter.
Home-page: https://github.com/romanstrazanec/bf2c
Author: Roman Stražanec
Author-email: roman.strazanec007@gmail.com
License: MIT
Download-URL: https://github.com/romanstrazanec/bf2c/releases/tag/v0.0.1
Keywords: bf brainfuck converter
Platform: UNKNOWN
Classifier: Development Status :: 4 - Beta
Classifier: Environment :: Console
Classifier: Intended Audience :: Developers
Classifier: License :: OSI Approved :: MIT License
Classifier: Programming Language :: Python :: 3.8
Classifier: Topic :: Other/Nonlisted Topic
